werag/.DS_Store
werag/__init__.py
werag/client.py
werag/crud.py
werag/db.py
werag/schema.py
werag/schemas/__init__.py
werag/schemas/chunk.py
werag/utils.py
werag-0.0.6.dist-info/METADATA
werag-0.0.6.dist-info/WHEEL
werag-0.0.6.dist-info/RECORD
