Metadata-Version: 2.1
Name: werag
Version: 0.0.6
Summary: python rag for wechat application
Author: zhenhao-ma
Author-email: bob0103779@gmail.com
Requires-Python: >=3.10,<3.13
Classifier: Programming Language :: Python :: 3
Classifier: Programming Language :: Python :: 3.10
Classifier: Programming Language :: Python :: 3.11
Classifier: Programming Language :: Python :: 3.12
Requires-Dist: bs4 (>=0,<1)
Requires-Dist: html2text (>=2024.2.26,<2025.0.0)
Requires-Dist: keble-helpers (>=0,<1)
Requires-Dist: langchain-chroma (>=0,<1)
Requires-Dist: langchain-community (>=0,<1)
Requires-Dist: langchain-openai (>=0.0.2.post1,<0.0.3)
Requires-Dist: pydantic (>=2.3.0,<3.0.0)
Requires-Dist: tenacity (>=8.2.3,<9.0.0)
Requires-Dist: wechatpy (>=1.8.18,<2.0.0)
